{"_id":{"$oid":"5c8f60b99520a918c00e77b2"},"addtime":{"$date":"2019-03-18T09:11:17.952Z"},"amount":0,"goods":[{"id":{"$oid":"5c8761859b01502110670ae5"},"count":3,"unit_price":11,"subtotal":33},{"id":{"$oid":"5c8775a7b8dd4033a044f49b"},"count":9,"unit_price":3,"subtotal":27}],"return_goods":[],"freight":8,"leave_word":"包装好点","return_leave_word":"","total_price":60,"return_total_price":0,"type":1,"state":1,"buyid":{"$oid":"5c88bd5b5c695c14c4fb8f37"},"address":{"$oid":"5c8a1c2961abd505f41bbe00"},"__v":0}
{"_id":{"$oid":"5c8f60f89520a918c00e77b3"},"addtime":{"$date":"2019-03-18T09:11:17.952Z"},"amount":0,"goods":[{"id":{"$oid":"5c8761859b01502110670ae5"},"count":3,"unit_price":11,"subtotal":33},{"id":{"$oid":"5c8775a7b8dd4033a044f49b"},"count":9,"unit_price":3,"subtotal":27}],"return_goods":[],"freight":8,"leave_word":"包装好点","return_leave_word":"","total_price":60,"return_total_price":0,"type":1,"state":1,"buyid":{"$oid":"5c88bd5b5c695c14c4fb8f37"},"address":{"$oid":"5c8a1c2961abd505f41bbe00"},"__v":0}
{"_id":{"$oid":"5c8f60fa9520a918c00e77b4"},"addtime":{"$date":"2019-03-18T09:11:17.952Z"},"amount":0,"goods":[{"id":{"$oid":"5c8761859b01502110670ae5"},"count":3,"unit_price":11,"subtotal":33},{"id":{"$oid":"5c8775a7b8dd4033a044f49b"},"count":9,"unit_price":3,"subtotal":27}],"return_goods":[],"freight":8,"leave_word":"包装好点","return_leave_word":"","total_price":60,"return_total_price":0,"type":1,"state":1,"buyid":{"$oid":"5c88bd5b5c695c14c4fb8f37"},"address":{"$oid":"5c8a1c2961abd505f41bbe00"},"__v":0}
{"_id":{"$oid":"5c8f60fb9520a918c00e77b5"},"addtime":{"$date":"2019-03-18T09:11:17.952Z"},"amount":0,"goods":[{"id":{"$oid":"5c8761859b01502110670ae5"},"count":3,"unit_price":11,"subtotal":33},{"id":{"$oid":"5c8775a7b8dd4033a044f49b"},"count":9,"unit_price":3,"subtotal":27}],"return_goods":[],"freight":8,"leave_word":"包装好点","return_leave_word":"","total_price":60,"return_total_price":0,"type":1,"state":1,"buyid":{"$oid":"5c88bd5b5c695c14c4fb8f37"},"address":{"$oid":"5c8a1c2961abd505f41bbe00"},"__v":0}
{"_id":{"$oid":"5c8f60fc9520a918c00e77b6"},"addtime":{"$date":"2019-03-18T09:11:17.952Z"},"amount":0,"goods":[{"id":{"$oid":"5c8761859b01502110670ae5"},"count":3,"unit_price":11,"subtotal":33},{"id":{"$oid":"5c8775a7b8dd4033a044f49b"},"count":9,"unit_price":3,"subtotal":27}],"return_goods":[],"freight":8,"leave_word":"包装好点","return_leave_word":"","total_price":60,"return_total_price":0,"type":1,"state":1,"buyid":{"$oid":"5c88bd5b5c695c14c4fb8f37"},"address":{"$oid":"5c8a1c2961abd505f41bbe00"},"__v":0}
{"_id":{"$oid":"5c8f60fd9520a918c00e77b7"},"addtime":{"$date":"2019-03-18T09:11:17.952Z"},"amount":0,"goods":[{"id":{"$oid":"5c8761859b01502110670ae5"},"count":3,"unit_price":11,"subtotal":33},{"id":{"$oid":"5c8775a7b8dd4033a044f49b"},"count":9,"unit_price":3,"subtotal":27}],"return_goods":[],"freight":8,"leave_word":"包装好点","return_leave_word":"","total_price":60,"return_total_price":0,"type":1,"state":1,"buyid":{"$oid":"5c88bd5b5c695c14c4fb8f37"},"address":{"$oid":"5c8a1c2961abd505f41bbe00"},"__v":0}
{"_id":{"$oid":"5c8f60fe9520a918c00e77b8"},"addtime":{"$date":"2019-03-18T09:11:17.952Z"},"amount":0,"goods":[{"id":{"$oid":"5c8761859b01502110670ae5"},"count":3,"unit_price":11,"subtotal":33},{"id":{"$oid":"5c8775a7b8dd4033a044f49b"},"count":9,"unit_price":3,"subtotal":27}],"return_goods":[],"freight":8,"leave_word":"包装好点","return_leave_word":"","total_price":60,"return_total_price":0,"type":1,"state":1,"buyid":{"$oid":"5c88bd5b5c695c14c4fb8f37"},"address":{"$oid":"5c8a1c2961abd505f41bbe00"},"__v":0}
{"_id":{"$oid":"5c8f60ff9520a918c00e77b9"},"addtime":{"$date":"2019-03-18T09:11:17.952Z"},"amount":0,"goods":[{"id":{"$oid":"5c8761859b01502110670ae5"},"count":3,"unit_price":11,"subtotal":33},{"id":{"$oid":"5c8775a7b8dd4033a044f49b"},"count":9,"unit_price":3,"subtotal":27}],"return_goods":[],"freight":8,"leave_word":"包装好点","return_leave_word":"","total_price":60,"return_total_price":0,"type":1,"state":1,"buyid":{"$oid":"5c88bd5b5c695c14c4fb8f37"},"address":{"$oid":"5c8a1c2961abd505f41bbe00"},"__v":0}
{"_id":{"$oid":"5c8f61009520a918c00e77ba"},"addtime":{"$date":"2019-03-18T09:11:17.952Z"},"amount":0,"goods":[{"id":{"$oid":"5c8761859b01502110670ae5"},"count":3,"unit_price":11,"subtotal":33},{"id":{"$oid":"5c8775a7b8dd4033a044f49b"},"count":9,"unit_price":3,"subtotal":27}],"return_goods":[],"freight":8,"leave_word":"包装好点","return_leave_word":"","total_price":60,"return_total_price":0,"type":1,"state":1,"buyid":{"$oid":"5c88bd5b5c695c14c4fb8f37"},"address":{"$oid":"5c8a1c2961abd505f41bbe00"},"__v":0}
{"_id":{"$oid":"5c8f61019520a918c00e77bb"},"addtime":{"$date":"2019-03-18T09:11:17.952Z"},"amount":0,"goods":[{"id":{"$oid":"5c8761859b01502110670ae5"},"count":3,"unit_price":11,"subtotal":33},{"id":{"$oid":"5c8775a7b8dd4033a044f49b"},"count":9,"unit_price":3,"subtotal":27}],"return_goods":[],"freight":8,"leave_word":"包装好点","return_leave_word":"","total_price":60,"return_total_price":0,"type":1,"state":1,"buyid":{"$oid":"5c88bd5b5c695c14c4fb8f37"},"address":{"$oid":"5c8a1c2961abd505f41bbe00"},"__v":0}
{"_id":{"$oid":"5c8f61019520a918c00e77bc"},"addtime":{"$date":"2019-03-18T09:11:17.952Z"},"amount":0,"goods":[{"id":{"$oid":"5c8761859b01502110670ae5"},"count":3,"unit_price":11,"subtotal":33},{"id":{"$oid":"5c8775a7b8dd4033a044f49b"},"count":9,"unit_price":3,"subtotal":27}],"return_goods":[],"freight":8,"leave_word":"包装好点","return_leave_word":"","total_price":60,"return_total_price":0,"type":1,"state":1,"buyid":{"$oid":"5c88bd5b5c695c14c4fb8f37"},"address":{"$oid":"5c8a1c2961abd505f41bbe00"},"__v":0}
